makura/__init__.py
makura/api.py
makura/assembly.py
makura/taxonparse.py
makura-1.2.0.dist-info/LICENSE
makura-1.2.0.dist-info/METADATA
makura-1.2.0.dist-info/WHEEL
makura-1.2.0.dist-info/entry_points.txt
makura-1.2.0.dist-info/top_level.txt
makura-1.2.0.dist-info/RECORD
