Metadata-Version: 2.1
Name: makura
Version: 1.2.0
Summary: NCBI Genome downloader
Home-page: https://github.com/hunglin59638/makura
Author: Hung-Lin, Chen
Author-email: hunglin59638@gmail.com
Maintainer: Hung-Lin, Chen
Maintainer-email: hunglin59638@gmail.com
License: UNKNOWN
Platform: UNKNOWN
Requires-Python: >=3.8,<4
License-File: LICENSE
Requires-Dist: pandas (>=1.5.1)
Requires-Dist: ete3 (>=3.1.2)
Requires-Dist: requests (>=2.28.1)
Requires-Dist: tqdm (>=4.64.1)
Requires-Dist: Flask (>=2.2.3)
